{
    "JHU_CSSE-CSSE_Ensemble": {
        "target_end_date": [
            "2024-04-13",
            "2024-04-20",
            "2024-04-27",
            "2024-05-04"
        ],
        "q0.025": [
            5,
            2,
            0,
            0
        ],
        "q0.25": [
            11,
            9,
            8,
            7
        ],
        "q0.5": [
            15,
            14,
            14,
            14
        ],
        "q0.75": [
            19,
            20,
            21,
            23
        ],
        "q0.975": [
            29,
            35,
            41,
            47
        ]
    },
    "LUcompUncertLab-chimera": {
        "target_end_date": [
            "2024-04-06",
            "2024-04-13",
            "2024-04-20",
            "2024-04-27",
            "2024-05-04"
        ],
        "q0.025": [
            8.0,
            5.0,
            5.0,
            3.0,
            2.0
        ],
        "q0.25": [
            15.0,
            13.0,
            11.0,
            9.0,
            7.0
        ],
        "q0.5": [
            19.0,
            18.0,
            16.0,
            15.0,
            14.0
        ],
        "q0.75": [
            24.0,
            23.0,
            23.0,
            22.0,
            22.0
        ],
        "q0.975": [
            33.0,
            34.0,
            37.0,
            41.0,
            47.0
        ]
    },
    "UNC_IDD-InfluPaint": {
        "target_end_date": [
            "2024-04-13",
            "2024-04-20",
            "2024-04-27",
            "2024-05-04"
        ],
        "q0.025": [
            2.528577039116952,
            2.9365765522157927,
            0.6891417576641364,
            0.3764938768845769
        ],
        "q0.25": [
            6.827287656012345,
            8.05263433374826,
            3.704703302285956,
            3.807796291771121
        ],
        "q0.5": [
            10.561439662151962,
            12.199657694939557,
            6.611161974457531,
            6.432169336983751
        ],
        "q0.75": [
            15.599645455817654,
            17.007541115986005,
            10.754106217544178,
            9.52571321743106
        ],
        "q0.975": [
            27.98643226347682,
            32.29540951274416,
            19.74651032749175,
            18.61850923727236
        ]
    },
    "LosAlamos_NAU-CModel_Flu": {
        "target_end_date": [
            "2024-04-13",
            "2024-04-20",
            "2024-04-27",
            "2024-05-04"
        ],
        "q0.025": [
            12.3126099310778,
            11.4286712904478,
            10.5447326498178,
            9.66079400918786
        ],
        "q0.25": [
            23.7207784419252,
            23.0579127503943,
            18.3398367247225,
            17.4558980840926
        ],
        "q0.5": [
            28.1903983043619,
            29.1195765755342,
            24.4015005498624,
            19.6143343741375
        ],
        "q0.75": [
            31.5726963004549,
            32.4720619280594,
            27.5320376627669,
            20.0876109310808
        ],
        "q0.975": [
            34.828012708975,
            36.568129101242,
            30.7873540712869,
            23.3429273396009
        ]
    },
    "SGroup-RandomForest": {
        "target_end_date": [
            "2024-04-06",
            "2024-04-13",
            "2024-04-20",
            "2024-04-27",
            "2024-05-04"
        ],
        "q0.025": [
            3.5,
            2.9,
            1.0,
            0.6,
            0.0
        ],
        "q0.25": [
            11.2,
            11.2,
            8.8,
            7.6,
            6.1
        ],
        "q0.5": [
            14.1,
            14.5,
            11.6,
            9.9,
            7.9
        ],
        "q0.75": [
            18.4,
            20.6,
            15.8,
            14.7,
            12.2
        ],
        "q0.975": [
            31.9,
            35.2,
            30.3,
            29.7,
            32.6
        ]
    },
    "UGA_flucast-Copycat": {
        "target_end_date": [
            "2024-04-13",
            "2024-04-20",
            "2024-04-27",
            "2024-05-04"
        ],
        "q0.025": [
            3.0,
            2.0,
            2.0,
            2.0
        ],
        "q0.25": [
            9.0,
            8.0,
            8.0,
            8.0
        ],
        "q0.5": [
            14.0,
            13.0,
            13.0,
            13.0
        ],
        "q0.75": [
            21.0,
            19.0,
            19.0,
            19.0
        ],
        "q0.975": [
            36.0,
            38.0,
            34.0,
            32.0
        ]
    },
    "GT-FluFNP": {
        "target_end_date": [
            "2024-04-13",
            "2024-04-20",
            "2024-04-27",
            "2024-05-04"
        ],
        "q0.025": [
            2.1857,
            0.0,
            0.0,
            0.0
        ],
        "q0.25": [
            9.8338,
            7.8786,
            3.8717,
            0.0
        ],
        "q0.5": [
            14.208,
            12.8139,
            10.518,
            7.0354
        ],
        "q0.75": [
            18.583,
            17.8687,
            17.104,
            14.2693
        ],
        "q0.975": [
            26.5313,
            26.9507,
            29.5147,
            28.8474
        ]
    },
    "VTSanghani-Ensemble": {
        "target_end_date": [
            "2024-04-06",
            "2024-04-13",
            "2024-04-20",
            "2024-04-27",
            "2024-05-04"
        ],
        "q0.025": [
            14.055,
            13.735,
            5.81,
            2.835,
            4.13
        ],
        "q0.25": [
            15.365,
            15.24,
            6.81,
            6.765,
            11.365
        ],
        "q0.5": [
            15.97,
            16.35,
            11.785,
            13.365,
            16.66
        ],
        "q0.75": [
            17.095,
            17.380000000000003,
            17.255000000000003,
            19.75,
            21.785
        ],
        "q0.975": [
            18.535,
            20.72,
            26.745,
            27.96,
            28.055
        ]
    },
    "UMass-flusion": {
        "target_end_date": [
            "2024-04-13",
            "2024-04-20",
            "2024-04-27",
            "2024-05-04"
        ],
        "q0.025": [
            1.192555496450016,
            0.0,
            0.0,
            0.0
        ],
        "q0.25": [
            7.998542754502094,
            4.7013881172553935,
            2.172865612777953,
            0.7609819420390185
        ],
        "q0.5": [
            11.56169241406812,
            8.826973992334278,
            6.232357045559757,
            4.650981993156244
        ],
        "q0.75": [
            15.328617314141804,
            13.92197147813991,
            11.60014641574456,
            10.605757566867812
        ],
        "q0.975": [
            25.94942367449644,
            28.804993399832117,
            31.46782543233702,
            35.2810218450534
        ]
    },
    "UMass-trends_ensemble": {
        "target_end_date": [
            "2024-04-13",
            "2024-04-20",
            "2024-04-27",
            "2024-05-04"
        ],
        "q0.025": [
            3.0,
            0.0,
            0.0,
            0.0
        ],
        "q0.25": [
            7.0,
            3.0,
            1.0,
            0.0
        ],
        "q0.5": [
            14.0,
            13.5,
            13.0,
            12.5
        ],
        "q0.75": [
            22.0,
            23.5,
            25.0,
            26.5
        ],
        "q0.975": [
            32.5,
            44.5,
            52.0,
            57.5
        ]
    },
    "PSI-PROF": {
        "target_end_date": [
            "2024-04-13",
            "2024-04-20",
            "2024-04-27",
            "2024-05-04"
        ],
        "q0.025": [
            4.0,
            4.0,
            3.76,
            3.46
        ],
        "q0.25": [
            11.0,
            10.21,
            10.0,
            9.33
        ],
        "q0.5": [
            15.3,
            14.93,
            14.0,
            13.25
        ],
        "q0.75": [
            21.0,
            19.98,
            19.0,
            17.86
        ],
        "q0.975": [
            46.02,
            45.0,
            44.0,
            41.02
        ]
    },
    "UGA_flucast-INFLAenza": {
        "target_end_date": [
            "2024-04-13",
            "2024-04-20",
            "2024-04-27",
            "2024-05-04"
        ],
        "q0.025": [
            5.0,
            4.0,
            3.0,
            2.0
        ],
        "q0.25": [
            11.0,
            10.0,
            8.0,
            8.0
        ],
        "q0.5": [
            15.0,
            14.0,
            13.0,
            12.0
        ],
        "q0.75": [
            20.0,
            20.0,
            19.0,
            17.0
        ],
        "q0.975": [
            32.0,
            36.0,
            36.0,
            36.0
        ]
    },
    "SigSci-CREG": {
        "target_end_date": [
            "2024-04-13",
            "2024-04-20",
            "2024-04-27",
            "2024-05-04"
        ],
        "q0.025": [
            4.0,
            4.0,
            4.0,
            4.0
        ],
        "q0.25": [
            11.0,
            11.0,
            11.0,
            11.0
        ],
        "q0.5": [
            17.0,
            17.0,
            17.0,
            17.0
        ],
        "q0.75": [
            24.0,
            24.0,
            24.0,
            24.0
        ],
        "q0.975": [
            42.0,
            42.0,
            42.0,
            42.0
        ]
    },
    "cfa-flumech": {
        "target_end_date": [
            "2024-04-06",
            "2024-04-13",
            "2024-04-20",
            "2024-04-27",
            "2024-05-04"
        ],
        "q0.025": [
            6.0,
            3.0,
            2.0,
            1.0,
            0.0
        ],
        "q0.25": [
            11.0,
            7.0,
            5.0,
            4.0,
            3.0
        ],
        "q0.5": [
            14.0,
            10.0,
            8.0,
            6.0,
            5.0
        ],
        "q0.75": [
            17.0,
            14.0,
            12.0,
            10.0,
            9.0
        ],
        "q0.975": [
            24.0,
            22.0,
            21.0,
            22.0,
            22.0
        ]
    },
    "MOBS-GLEAM_FLUH": {
        "target_end_date": [
            "2024-04-06",
            "2024-04-13",
            "2024-04-20",
            "2024-04-27",
            "2024-05-04"
        ],
        "q0.025": [
            5.0,
            3.0,
            2.0,
            1.0,
            1.0
        ],
        "q0.25": [
            11.0,
            8.0,
            6.0,
            4.0,
            3.0
        ],
        "q0.5": [
            15.0,
            11.0,
            9.0,
            6.0,
            5.0
        ],
        "q0.75": [
            19.0,
            15.0,
            12.0,
            9.0,
            7.0
        ],
        "q0.975": [
            30.0,
            23.0,
            19.0,
            14.0,
            11.0
        ]
    },
    "PSI-PROF_beta": {
        "target_end_date": [
            "2024-04-13",
            "2024-04-20",
            "2024-04-27",
            "2024-05-04"
        ],
        "q0.025": [
            4.13,
            3.93,
            3.59,
            3.39
        ],
        "q0.25": [
            11.36,
            10.7,
            10.36,
            9.66
        ],
        "q0.5": [
            15.36,
            14.51,
            14.36,
            13.99
        ],
        "q0.75": [
            20.59,
            19.36,
            19.28,
            18.36
        ],
        "q0.975": [
            43.36,
            39.36,
            39.36,
            35.36
        ]
    },
    "MIGHTE-Nsemble": {
        "target_end_date": [
            "2024-04-06",
            "2024-04-13",
            "2024-04-20",
            "2024-04-27",
            "2024-05-04"
        ],
        "q0.025": [
            5.399500084565261,
            4.151330497177479,
            1.2955800701302662,
            1.215734626315952,
            0.063021573803832
        ],
        "q0.25": [
            13.213976756131066,
            11.513267909517422,
            8.954190360445484,
            7.464209474960429,
            4.789729821251189
        ],
        "q0.5": [
            19.03001995485841,
            17.11433648302667,
            15.39278052823709,
            14.142780528237097,
            10.642780528237088
        ],
        "q0.75": [
            26.1949286673308,
            24.073154762238403,
            23.59688475385009,
            24.49608362069156,
            20.446847917994184
        ],
        "q0.975": [
            44.03660640061928,
            41.516378436498655,
            44.33579639680357,
            59.48344757907155,
            56.55427098090934
        ]
    },
    "UGuelph-CompositeCurve": {
        "target_end_date": [
            "2024-04-06",
            "2024-04-13",
            "2024-04-20",
            "2024-04-27",
            "2024-05-04"
        ],
        "q0.025": [
            2.42109831027507,
            2.33586734823711,
            2.17605637866998,
            1.9607022326168,
            1.78064527868072
        ],
        "q0.25": [
            6.1708721764167,
            5.25794108934798,
            4.50806157352553,
            3.97819001612129,
            3.61793069165547
        ],
        "q0.5": [
            8.46581451188523,
            6.94039845635596,
            6.17801508225507,
            5.66372154149939,
            5.28020729646664
        ],
        "q0.75": [
            10.8072770301077,
            8.75617186186791,
            7.99490366857985,
            7.55086380739955,
            7.05226923635652
        ],
        "q0.975": [
            23.549944227453,
            15.5847634506048,
            12.8863820789669,
            11.6968763170385,
            10.6686510809344
        ]
    },
    "FluSight-lop_norm": {
        "target_end_date": [
            "2024-04-06",
            "2024-04-13",
            "2024-04-20",
            "2024-04-27",
            "2024-05-04"
        ],
        "q0.025": [
            4.134111251938963,
            2.6329060064380063,
            0.0,
            0.0,
            0.0
        ],
        "q0.25": [
            10.653534646535345,
            9.305469453054696,
            7.180629350791079,
            5.485726668693362,
            4.176941533469831
        ],
        "q0.5": [
            14.981201879812016,
            13.707906203103322,
            12.052003194209997,
            10.559664839792278,
            9.210609783531014
        ],
        "q0.75": [
            19.65497179839267,
            19.368436237747595,
            19.00908786286596,
            18.076414723664136,
            17.30714331313962
        ],
        "q0.975": [
            30.634288683235454,
            33.036575452698386,
            36.194593852575885,
            39.21109639197233,
            42.66686881842807
        ]
    },
    "cfarenewal-cfaepimlight": {
        "target_end_date": [
            "2024-04-06",
            "2024-04-13",
            "2024-04-20",
            "2024-04-27",
            "2024-05-04"
        ],
        "q0.025": [
            6.0,
            3.0,
            1.0,
            0.0,
            0.0
        ],
        "q0.25": [
            12.0,
            8.0,
            5.0,
            3.0,
            2.0
        ],
        "q0.5": [
            15.0,
            11.0,
            8.0,
            6.0,
            4.0
        ],
        "q0.75": [
            19.0,
            15.0,
            13.0,
            11.0,
            9.0
        ],
        "q0.975": [
            27.0,
            27.0,
            31.0,
            39.0,
            53.0
        ]
    },
    "CU-ensemble": {
        "target_end_date": [
            "2024-04-13",
            "2024-04-20",
            "2024-04-27",
            "2024-05-04"
        ],
        "q0.025": [
            10.046,
            7.341,
            5.654,
            4.74
        ],
        "q0.25": [
            12.948,
            11.141,
            9.455,
            7.871
        ],
        "q0.5": [
            14.775,
            14.03,
            13.179,
            12.58
        ],
        "q0.75": [
            16.69,
            17.164,
            17.5,
            17.289
        ],
        "q0.975": [
            20.622,
            23.347,
            24.992,
            25.885
        ]
    },
    "CMU-TimeSeries": {
        "target_end_date": [
            "2024-04-13",
            "2024-04-20",
            "2024-04-27",
            "2024-05-04"
        ],
        "q0.025": [
            3.557713639601697,
            1.6643890389102984,
            0.8608628506740483,
            0.5922479856214687
        ],
        "q0.25": [
            9.256509457999451,
            7.84634515303336,
            6.7459882011195225,
            6.060303666903844
        ],
        "q0.5": [
            12.928282832754352,
            12.127895387265614,
            11.698652241135688,
            11.669881637825789
        ],
        "q0.75": [
            17.445910692981,
            17.37546355147336,
            17.917731907571508,
            18.606241374802064
        ],
        "q0.975": [
            35.551248501533614,
            37.784527315455605,
            45.86010601272658,
            55.4045144146571
        ]
    },
    "FluSight-ensemble": {
        "target_end_date": [
            "2024-04-06",
            "2024-04-13",
            "2024-04-20",
            "2024-04-27",
            "2024-05-04"
        ],
        "q0.025": [
            5.0198557416913,
            3.0,
            2.0,
            0.6891417576641364,
            0.0
        ],
        "q0.25": [
            11.2,
            9.256509457999451,
            8.0,
            5.69555013747472,
            3.807796291771121
        ],
        "q0.5": [
            15.0,
            14.0,
            12.38576239347458,
            10.8742547754408,
            9.870373725891112
        ],
        "q0.75": [
            19.0,
            19.0,
            17.8687,
            17.5,
            17.0
        ],
        "q0.975": [
            30.0,
            31.0,
            35.0,
            36.0,
            36.0
        ]
    },
    "Stevens-GBR": {
        "target_end_date": [
            "2024-04-13",
            "2024-04-20",
            "2024-04-27",
            "2024-05-04"
        ],
        "q0.025": [
            8.05938235320473,
            6.506399245048728,
            6.297327386024115,
            5.063299562278136
        ],
        "q0.25": [
            10.35470196641564,
            8.680558236908878,
            9.66603910768686,
            7.316816538588021
        ],
        "q0.5": [
            12.375014641203585,
            9.98451968498487,
            11.918262599191724,
            9.99061125475168
        ],
        "q0.75": [
            15.290279422935152,
            15.393766050730273,
            14.94934506483575,
            12.813132416155456
        ],
        "q0.975": [
            39.88602053641024,
            43.36882467416835,
            38.08310685943961,
            43.00309102830085
        ]
    },
    "FluSight-baseline": {
        "target_end_date": [
            "2024-04-06",
            "2024-04-13",
            "2024-04-20",
            "2024-04-27",
            "2024-05-04"
        ],
        "q0.025": [
            16.0,
            0.0,
            0.0,
            0.0,
            0.0
        ],
        "q0.25": [
            16.0,
            14.0,
            11.0,
            9.0,
            7.0
        ],
        "q0.5": [
            16.0,
            16.0,
            16.0,
            16.0,
            16.0
        ],
        "q0.75": [
            16.0,
            18.0,
            21.0,
            23.0,
            25.0
        ],
        "q0.975": [
            16.0,
            40.0,
            48.42656076560768,
            52.752149021490176,
            57.16381838818386
        ]
    },
    "ISU_NiemiLab-NLH": {
        "target_end_date": [
            "2024-04-06",
            "2024-04-13",
            "2024-04-20",
            "2024-04-27",
            "2024-05-04"
        ],
        "q0.025": [
            5.0198557416913,
            3.32182156807586,
            0.0,
            0.0,
            0.0
        ],
        "q0.25": [
            12.9475941596717,
            11.0947829584287,
            8.05402502073941,
            5.69555013747472,
            3.47594170748102
        ],
        "q0.5": [
            17.4258354997338,
            15.3858286541342,
            13.1992630388411,
            10.8742547754408,
            8.73750400832071
        ],
        "q0.75": [
            22.448239478387,
            19.9450665896131,
            18.6462363133968,
            16.6881704757458,
            14.4564016323632
        ],
        "q0.975": [
            34.0013928020953,
            30.1572430178322,
            31.7943290877278,
            30.1271534617729,
            27.515090823691
        ]
    },
    "UVAFluX-Ensemble": {
        "target_end_date": [
            "2024-04-06",
            "2024-04-13",
            "2024-04-20",
            "2024-04-27",
            "2024-05-04"
        ],
        "q0.025": [
            2.0,
            1.0,
            0.0,
            0.0,
            0.0
        ],
        "q0.25": [
            10.0,
            9.0,
            4.0,
            3.0,
            2.0
        ],
        "q0.5": [
            16.0,
            14.0,
            10.0,
            9.0,
            8.0
        ],
        "q0.75": [
            21.0,
            19.0,
            16.0,
            16.0,
            14.0
        ],
        "q0.975": [
            32.0,
            31.0,
            30.0,
            29.0,
            29.0
        ]
    },
    "UM-DeepOutbreak": {
        "target_end_date": [
            "2024-04-13",
            "2024-04-20",
            "2024-04-27",
            "2024-05-04"
        ],
        "q0.025": [
            0.0,
            0.0,
            0.0,
            0.0
        ],
        "q0.25": [
            4.105492115020745,
            0.0,
            0.0,
            0.0
        ],
        "q0.5": [
            14.236661791801453,
            12.38576239347458,
            10.86804175376892,
            9.870373725891112
        ],
        "q0.75": [
            24.28618001937867,
            29.374459505081177,
            30.21167125701905,
            31.45070772171021
        ],
        "q0.975": [
            33.613064765930176,
            44.330443382263184,
            55.33384037017822,
            62.75953531265259
        ]
    },
    "SigSci-TSENS": {
        "target_end_date": [
            "2024-04-13",
            "2024-04-20",
            "2024-04-27",
            "2024-05-04"
        ],
        "q0.025": [
            0.0,
            0.0,
            0.0,
            0.0
        ],
        "q0.25": [
            9.0,
            3.0,
            0.0,
            0.0
        ],
        "q0.5": [
            14.0,
            12.0,
            10.0,
            6.0
        ],
        "q0.75": [
            19.0,
            22.0,
            24.0,
            24.0
        ],
        "q0.975": [
            29.0,
            39.0,
            49.0,
            56.0
        ]
    },
    "fjordhest-ensemble": {
        "target_end_date": [
            "2024-04-06",
            "2024-04-13",
            "2024-04-20",
            "2024-04-27",
            "2024-05-04"
        ],
        "q0.025": [
            8.0,
            5.16,
            1.58,
            0.6,
            0.0
        ],
        "q0.25": [
            13.0,
            12.1,
            9.17,
            6.7,
            5.5
        ],
        "q0.5": [
            16.0,
            15.76,
            15.6,
            14.09,
            12.81
        ],
        "q0.75": [
            20.0,
            20.99,
            21.09,
            21.2,
            21.36
        ],
        "q0.975": [
            28.0,
            29.93,
            34.15,
            39.53,
            42.66
        ]
    },
    "NU_UCSD-GLEAM_AI_FLUH": {
        "target_end_date": [
            "2024-04-06",
            "2024-04-13",
            "2024-04-20",
            "2024-04-27",
            "2024-05-04"
        ],
        "q0.025": [
            4.548,
            1.835,
            2.72,
            1.765,
            2.108
        ],
        "q0.25": [
            12.838,
            11.214,
            12.471,
            11.672,
            10.693
        ],
        "q0.5": [
            17.324,
            18.434,
            19.451,
            18.296,
            18.41
        ],
        "q0.75": [
            23.459,
            28.365,
            29.84,
            28.204,
            27.184
        ],
        "q0.975": [
            41.927,
            53.555,
            52.29,
            52.375,
            49.996
        ]
    },
    "CEPH-Rtrend_fluH": {
        "target_end_date": [
            "2024-04-13",
            "2024-04-20",
            "2024-04-27",
            "2024-05-04"
        ],
        "q0.025": [
            2.0,
            0.0,
            0.0,
            0.0
        ],
        "q0.25": [
            8.0,
            4.0,
            1.0,
            0.0
        ],
        "q0.5": [
            13.0,
            10.0,
            7.0,
            4.0
        ],
        "q0.75": [
            18.0,
            17.0,
            16.0,
            14.0
        ],
        "q0.975": [
            31.0,
            39.0,
            44.0,
            48.0
        ]
    }
}