{
    "JHU_CSSE-CSSE_Ensemble": {
        "target_end_date": [
            "2024-02-03",
            "2024-02-10",
            "2024-02-17",
            "2024-02-24"
        ],
        "q0.025": [
            431.1775,
            350.4875,
            301.285,
            262.1625
        ],
        "q0.25": [
            552.225,
            475.5,
            432.35,
            402.0
        ],
        "q0.5": [
            629.6,
            555.95,
            515.2,
            492.9
        ],
        "q0.75": [
            717.3,
            647.45,
            614.1,
            599.8
        ],
        "q0.975": [
            898.6575,
            845.865,
            833.9075,
            849.2175
        ]
    },
    "LUcompUncertLab-chimera": {
        "target_end_date": [
            "2024-01-27",
            "2024-02-03",
            "2024-02-10",
            "2024-02-17",
            "2024-02-24"
        ],
        "q0.025": [
            0.0,
            0.0,
            0.0,
            0.0,
            0.0
        ],
        "q0.25": [
            745.0,
            568.0,
            402.0,
            287.0,
            203.0
        ],
        "q0.5": [
            812.0,
            683.0,
            554.0,
            457.0,
            377.5
        ],
        "q0.75": [
            852.0,
            789.0,
            716.0,
            649.0,
            590.0
        ],
        "q0.975": [
            975.0,
            1022.0,
            1256.0,
            1618.0,
            2098.774999999998
        ]
    },
    "UNC_IDD-InfluPaint": {
        "target_end_date": [
            "2024-02-03",
            "2024-02-10",
            "2024-02-17",
            "2024-02-24"
        ],
        "q0.025": [
            411.2868597374863,
            298.6268625890608,
            214.23768200284573,
            173.39984205042617
        ],
        "q0.25": [
            489.8718476806481,
            373.3450844095376,
            293.79035449064486,
            252.07349945946555
        ],
        "q0.5": [
            533.3444588486636,
            418.7686747579711,
            343.89593173600366,
            312.761215633445
        ],
        "q0.75": [
            576.5623851403999,
            467.92769769424257,
            406.5738308261629,
            414.3745310054213
        ],
        "q0.975": [
            667.0763891657305,
            581.3983471746383,
            604.6268713872494,
            698.5376448459655
        ]
    },
    "LosAlamos_NAU-CModel_Flu": {
        "target_end_date": [
            "2024-02-03",
            "2024-02-10",
            "2024-02-17",
            "2024-02-24"
        ],
        "q0.025": [
            759.469664446656,
            696.974955669463,
            632.676278252836,
            567.733407233206
        ],
        "q0.25": [
            797.321275906417,
            739.003646821829,
            672.300845657968,
            607.357974638338
        ],
        "q0.5": [
            862.525105319915,
            804.207476235328,
            742.12976129838,
            678.906672158589
        ],
        "q0.75": [
            906.172380281516,
            850.125176476056,
            788.047461539107,
            726.461093148191
        ],
        "q0.975": [
            1307.95453867754,
            1264.30070501973,
            1209.85289607935,
            1164.79107995879
        ]
    },
    "SGroup-RandomForest": {
        "target_end_date": [
            "2024-01-27",
            "2024-02-03",
            "2024-02-10",
            "2024-02-17",
            "2024-02-24"
        ],
        "q0.025": [
            305.6,
            411.0,
            133.5,
            25.5,
            0.0
        ],
        "q0.25": [
            520.3,
            644.0,
            330.0,
            238.7,
            114.9
        ],
        "q0.5": [
            672.4,
            775.6,
            414.5,
            360.4,
            268.4
        ],
        "q0.75": [
            817.5,
            896.8,
            546.7,
            566.9,
            530.8
        ],
        "q0.975": [
            1134.8,
            1241.8,
            1096.3,
            1268.5,
            1082.6
        ]
    },
    "UGA_flucast-Copycat": {
        "target_end_date": [
            "2024-02-03",
            "2024-02-10",
            "2024-02-17",
            "2024-02-24"
        ],
        "q0.025": [
            609.0,
            483.0,
            366.0,
            280.0
        ],
        "q0.25": [
            673.0,
            561.0,
            481.0,
            426.0
        ],
        "q0.5": [
            711.0,
            610.0,
            538.0,
            487.0
        ],
        "q0.75": [
            752.0,
            668.0,
            607.0,
            567.0
        ],
        "q0.975": [
            890.0,
            896.0,
            903.0,
            951.0
        ]
    },
    "GT-FluFNP": {
        "target_end_date": [
            "2024-02-03",
            "2024-02-10",
            "2024-02-17",
            "2024-02-24"
        ],
        "q0.025": [
            524.6401,
            210.912,
            0.0,
            0.0
        ],
        "q0.25": [
            700.6612,
            413.9536,
            177.1357,
            87.1058
        ],
        "q0.5": [
            793.2411,
            524.5657,
            320.0353,
            259.9096
        ],
        "q0.75": [
            891.4957,
            631.8482,
            461.9342,
            432.3182
        ],
        "q0.975": [
            1047.2086,
            835.9009,
            726.2032,
            742.7967
        ]
    },
    "UMass-flusion": {
        "target_end_date": [
            "2024-02-03",
            "2024-02-10",
            "2024-02-17",
            "2024-02-24"
        ],
        "q0.025": [
            457.59104984468416,
            333.39836890035946,
            234.5555645145454,
            187.83671458241557
        ],
        "q0.25": [
            646.009506718604,
            532.4877775039431,
            411.9839341169126,
            340.761275113427
        ],
        "q0.5": [
            719.5928063931424,
            624.8465596826684,
            528.8794560660282,
            460.7518124268697
        ],
        "q0.75": [
            794.5699306306722,
            733.9705844065512,
            656.5054989469054,
            600.3424306151031
        ],
        "q0.975": [
            1005.602268223914,
            1063.0895225717684,
            1102.1430671334797,
            1149.120513635917
        ]
    },
    "UMass-trends_ensemble": {
        "target_end_date": [
            "2024-02-03",
            "2024-02-10",
            "2024-02-17",
            "2024-02-24"
        ],
        "q0.025": [
            555.0,
            344.0,
            221.5,
            128.5
        ],
        "q0.25": [
            715.5,
            630.0,
            559.0,
            497.5
        ],
        "q0.5": [
            832.0,
            810.0,
            787.0,
            764.5
        ],
        "q0.75": [
            939.5,
            981.0,
            1003.5,
            1018.0
        ],
        "q0.975": [
            1135.5,
            1301.0,
            1418.5,
            1512.0
        ]
    },
    "PSI-PROF": {
        "target_end_date": [
            "2024-02-03",
            "2024-02-10",
            "2024-02-17",
            "2024-02-24"
        ],
        "q0.025": [
            371.95,
            287.0,
            212.0,
            168.95
        ],
        "q0.25": [
            595.0,
            497.0,
            411.5,
            342.75
        ],
        "q0.5": [
            743.5,
            661.0,
            582.5,
            506.0
        ],
        "q0.75": [
            898.0,
            833.25,
            762.25,
            690.0
        ],
        "q0.975": [
            1152.05,
            1103.27,
            1054.05,
            1000.1
        ]
    },
    "UGA_flucast-INFLAenza": {
        "target_end_date": [
            "2024-02-03",
            "2024-02-10",
            "2024-02-17",
            "2024-02-24"
        ],
        "q0.025": [
            379.0,
            265.0,
            199.0,
            145.0
        ],
        "q0.25": [
            555.0,
            442.0,
            378.0,
            318.0
        ],
        "q0.5": [
            690.0,
            577.0,
            509.0,
            462.0
        ],
        "q0.75": [
            833.0,
            763.0,
            697.0,
            685.0
        ],
        "q0.975": [
            1189.0,
            1350.0,
            1393.0,
            1418.0
        ]
    },
    "cfa-flumech": {
        "target_end_date": [
            "2024-02-03",
            "2024-02-10",
            "2024-02-17",
            "2024-02-24"
        ],
        "q0.025": [
            409.975,
            332.99999999999994,
            279.975,
            203.975
        ],
        "q0.25": [
            579.0,
            494.75,
            422.75000000000006,
            330.75
        ],
        "q0.5": [
            683.0,
            597.5,
            515.5,
            436.0
        ],
        "q0.75": [
            809.0,
            727.2500000000001,
            628.25,
            551.0
        ],
        "q0.975": [
            1086.9999999999998,
            996.1249999999995,
            917.075,
            828.2249999999999
        ]
    },
    "MOBS-GLEAM_FLUH": {
        "target_end_date": [
            "2024-01-27",
            "2024-02-03",
            "2024-02-10",
            "2024-02-17",
            "2024-02-24"
        ],
        "q0.025": [
            533.428,
            439.112,
            358.584,
            292.511,
            228.012
        ],
        "q0.25": [
            739.31,
            648.638,
            562.789,
            470.896,
            383.443
        ],
        "q0.5": [
            865.38,
            794.429,
            710.962,
            612.614,
            504.292
        ],
        "q0.75": [
            999.764,
            946.528,
            871.061,
            767.464,
            637.606
        ],
        "q0.975": [
            1237.254,
            1248.17,
            1183.867,
            1083.311,
            921.891
        ]
    },
    "PSI-PROF_beta": {
        "target_end_date": [
            "2024-02-03",
            "2024-02-10",
            "2024-02-17",
            "2024-02-24"
        ],
        "q0.025": [
            555.23,
            457.26,
            370.26,
            293.26
        ],
        "q0.25": [
            696.45,
            634.26,
            552.01,
            466.01
        ],
        "q0.5": [
            777.33,
            729.26,
            691.89,
            654.92
        ],
        "q0.75": [
            857.26,
            813.27,
            803.84,
            792.83
        ],
        "q0.975": [
            1014.36,
            971.96,
            946.9,
            953.2
        ]
    },
    "MIGHTE-Nsemble": {
        "target_end_date": [
            "2024-01-27",
            "2024-02-03",
            "2024-02-10",
            "2024-02-17",
            "2024-02-24"
        ],
        "q0.025": [
            662.2082104033378,
            430.5642099064453,
            329.9290833217501,
            304.4382791824424,
            294.49372921815205
        ],
        "q0.25": [
            813.3865354695268,
            606.7251489802633,
            519.024130773897,
            500.4287742667944,
            495.2944294799846
        ],
        "q0.5": [
            903.0629073403768,
            719.809769241226,
            648.12861702239,
            637.5170756108008,
            637.5170756108008
        ],
        "q0.75": [
            1000.4705882696336,
            849.134814356904,
            801.6891144291515,
            803.0723240435432,
            810.6226213288548
        ],
        "q0.975": [
            1209.3042110870051,
            1146.7629302459682,
            1174.2784892072589,
            1212.959069982022,
            1243.6554309509152
        ]
    },
    "UGuelph-CompositeCurve": {
        "target_end_date": [
            "2024-02-03",
            "2024-02-10",
            "2024-02-17",
            "2024-02-24"
        ],
        "q0.025": [
            436.897412647779,
            216.238461645788,
            126.688942741036,
            11.7183075058896
        ],
        "q0.25": [
            641.826073677829,
            499.336760041395,
            434.065049873234,
            379.939178641391
        ],
        "q0.5": [
            745.159777668626,
            641.906586967192,
            588.652955793245,
            564.861426761694
        ],
        "q0.75": [
            848.493481659425,
            784.476413892989,
            743.240861713257,
            749.783674881998
        ],
        "q0.975": [
            1053.42214268947,
            1067.5747122886,
            1050.61696884545,
            1118.0045460175
        ]
    },
    "FluSight-lop_norm": {
        "target_end_date": [
            "2024-01-27",
            "2024-02-03",
            "2024-02-10",
            "2024-02-17",
            "2024-02-24"
        ],
        "q0.025": [
            335.9439161771778,
            365.4093017578125,
            190.84387119602172,
            83.12621254672621,
            15.793893447319013
        ],
        "q0.25": [
            721.4163407207933,
            615.6668216235687,
            468.6601616342062,
            378.6689332906825,
            309.728019704268
        ],
        "q0.5": [
            814.8708746908985,
            725.3287549291824,
            622.026535715288,
            548.7475955037673,
            499.5611379262233
        ],
        "q0.75": [
            902.2361588272604,
            845.4297741966767,
            787.7805741863208,
            743.2204020754368,
            707.6080727494509
        ],
        "q0.975": [
            1152.9843408345143,
            1114.124124033124,
            1178.2412990871248,
            1301.961669921875,
            1444.2678833007812
        ]
    },
    "cfarenewal-cfaepimlight": {
        "target_end_date": [
            "2024-01-27",
            "2024-02-03",
            "2024-02-10",
            "2024-02-17",
            "2024-02-24"
        ],
        "q0.025": [
            721.0,
            543.975,
            338.0,
            179.97500000000002,
            86.97500000000001
        ],
        "q0.25": [
            789.0,
            696.0,
            562.0,
            408.0,
            275.0
        ],
        "q0.5": [
            826.0,
            801.0,
            732.0,
            631.0,
            512.0
        ],
        "q0.75": [
            866.0,
            917.0,
            960.0,
            958.0,
            904.5000000000008
        ],
        "q0.975": [
            951.025,
            1224.0750000000005,
            1733.1000000000004,
            2265.575000000002,
            2753.275000000001
        ]
    },
    "CU-ensemble": {
        "target_end_date": [
            "2024-02-03",
            "2024-02-10",
            "2024-02-17",
            "2024-02-24"
        ],
        "q0.025": [
            544.012,
            476.162,
            432.529,
            401.46
        ],
        "q0.25": [
            712.72,
            666.077,
            626.48,
            605.408
        ],
        "q0.5": [
            764.974,
            716.686,
            682.935,
            668.483
        ],
        "q0.75": [
            836.85,
            789.975,
            762.744,
            742.283
        ],
        "q0.975": [
            970.587,
            968.396,
            968.311,
            970.434
        ]
    },
    "CMU-TimeSeries": {
        "target_end_date": [
            "2024-02-03",
            "2024-02-10",
            "2024-02-17",
            "2024-02-24"
        ],
        "q0.025": [
            389.8844443924619,
            211.45889410969025,
            123.056133495197,
            70.33365443819422
        ],
        "q0.25": [
            613.8608671163884,
            509.3365161332175,
            403.6484028477263,
            438.1806005426765
        ],
        "q0.5": [
            722.9769677710157,
            649.0138342949057,
            539.2082939127962,
            667.9774793485262
        ],
        "q0.75": [
            861.7925475949913,
            876.9024442044712,
            882.1411398663598,
            1020.2014448357024
        ],
        "q0.975": [
            1347.3915597227003,
            1753.280208304663,
            2110.206301167435,
            2318.975046489289
        ]
    },
    "FluSight-ensemble": {
        "target_end_date": [
            "2024-01-27",
            "2024-02-03",
            "2024-02-10",
            "2024-02-17",
            "2024-02-24"
        ],
        "q0.025": [
            533.428,
            438.0047063238896,
            331.46454166087506,
            217.86884100142288,
            167.45499999999998
        ],
        "q0.25": [
            739.31,
            628.2770368389145,
            500.6683800206975,
            411.74196705845634,
            341.7556375567135
        ],
        "q0.5": [
            812.0,
            728.6037338855078,
            645.017601994791,
            560.8541469563982,
            505.146
        ],
        "q0.75": [
            880.34625,
            839.35275,
            787.2257069464945,
            752.7454308566284,
            687.5
        ],
        "q0.975": [
            1130.0,
            1070.211071344735,
            1099.785,
            1092.7270335667397,
            1100.30227300875
        ]
    },
    "Stevens-GBR": {
        "target_end_date": [
            "2024-02-03",
            "2024-02-10",
            "2024-02-17",
            "2024-02-24"
        ],
        "q0.025": [
            48.56643802157448,
            38.38074680003708,
            35.62779651840668,
            29.89276917632378
        ],
        "q0.25": [
            530.4955353234742,
            379.9128460200607,
            259.2252111018773,
            204.75027796367445
        ],
        "q0.5": [
            618.5313463934302,
            426.1263785243819,
            326.9433027015453,
            264.58652960757865
        ],
        "q0.75": [
            635.9511027968283,
            459.46269046072285,
            357.6640178846053,
            304.27599298018976
        ],
        "q0.975": [
            641.6323857332136,
            521.8967857223457,
            431.8351129718194,
            418.4211520878122
        ]
    },
    "FluSight-baseline": {
        "target_end_date": [
            "2024-01-27",
            "2024-02-03",
            "2024-02-10",
            "2024-02-17",
            "2024-02-24"
        ],
        "q0.025": [
            833.0,
            644.6750000000001,
            533.6816875668756,
            474.7521575215752,
            423.23545835458367
        ],
        "q0.25": [
            833.0,
            810.0,
            772.3762762627628,
            746.720199701997,
            725.8987989879898
        ],
        "q0.5": [
            833.0,
            833.0,
            833.0,
            833.0,
            833.0
        ],
        "q0.75": [
            833.0,
            856.0,
            894.0,
            919.7538550385505,
            941.150361503615
        ],
        "q0.975": [
            833.0,
            1021.325,
            1135.1480879808794,
            1191.5988224882262,
            1241.9417286672865
        ]
    },
    "ISU_NiemiLab-NLH": {
        "target_end_date": [
            "2024-01-27",
            "2024-02-03",
            "2024-02-10",
            "2024-02-17",
            "2024-02-24"
        ],
        "q0.025": [
            509.1767,
            440.867725,
            382.191625,
            368.52495,
            347.375225
        ],
        "q0.25": [
            682.30625,
            614.728,
            601.3985,
            578.9725,
            541.77975
        ],
        "q0.5": [
            774.845,
            734.2305,
            697.156,
            689.018,
            651.414
        ],
        "q0.75": [
            880.34625,
            838.9355,
            807.44625,
            790.33,
            776.15225
        ],
        "q0.975": [
            1088.695,
            1026.34025,
            1031.592,
            1035.14025,
            1051.58775
        ]
    },
    "UVAFluX-Ensemble": {
        "target_end_date": [
            "2024-01-27",
            "2024-02-03",
            "2024-02-10",
            "2024-02-17",
            "2024-02-24"
        ],
        "q0.025": [
            625.0,
            457.0,
            339.0,
            232.0,
            167.0
        ],
        "q0.25": [
            750.0,
            611.0,
            502.0,
            399.0,
            318.0
        ],
        "q0.5": [
            833.0,
            776.0,
            771.0,
            701.0,
            631.0
        ],
        "q0.75": [
            940.0,
            887.0,
            934.0,
            957.0,
            1022.0
        ],
        "q0.975": [
            1130.0,
            1129.0,
            1158.0,
            1267.0,
            1336.0
        ]
    },
    "UM-DeepOutbreak": {
        "target_end_date": [
            "2024-02-03",
            "2024-02-10",
            "2024-02-17",
            "2024-02-24"
        ],
        "q0.025": [
            365.4093017578125,
            181.40753173828125,
            34.0498046875,
            0.0
        ],
        "q0.25": [
            579.2761993408203,
            414.7698333740233,
            359.6269454956051,
            176.9014587402342
        ],
        "q0.5": [
            661.4861907958984,
            677.0642852783203,
            685.4364471435547,
            650.2416381835938
        ],
        "q0.75": [
            738.0382537841797,
            936.8167144775392,
            976.38452911377,
            1086.3862609863284
        ],
        "q0.975": [
            951.9051513671876,
            1170.1790161132812,
            1301.961669921875,
            1444.2678833007812
        ]
    },
    "SigSci-TSENS": {
        "target_end_date": [
            "2024-02-03",
            "2024-02-10",
            "2024-02-17",
            "2024-02-24"
        ],
        "q0.025": [
            558.0,
            420.0,
            320.0,
            218.0
        ],
        "q0.25": [
            734.0,
            681.0,
            650.0,
            608.0
        ],
        "q0.5": [
            826.0,
            819.0,
            823.0,
            812.0
        ],
        "q0.75": [
            919.0,
            956.0,
            996.0,
            1016.0
        ],
        "q0.975": [
            1095.0,
            1218.0,
            1327.0,
            1406.0
        ]
    },
    "fjordhest-ensemble": {
        "target_end_date": [
            "2024-01-27",
            "2024-02-03",
            "2024-02-10",
            "2024-02-17",
            "2024-02-24"
        ],
        "q0.025": [
            603.0,
            578.97,
            359.04,
            248.88,
            167.91
        ],
        "q0.25": [
            720.0,
            697.12,
            557.68,
            467.96,
            372.63
        ],
        "q0.5": [
            790.0,
            763.28,
            662.37,
            597.68,
            532.92
        ],
        "q0.75": [
            872.0,
            839.77,
            797.11,
            793.65,
            766.92
        ],
        "q0.975": [
            1057.02,
            1036.22,
            1172.37,
            1395.3,
            1321.01
        ]
    },
    "NU_UCSD-GLEAM_AI_FLUH": {
        "target_end_date": [
            "2024-01-27",
            "2024-02-03",
            "2024-02-10",
            "2024-02-17",
            "2024-02-24"
        ],
        "q0.025": [
            389.645,
            246.864,
            120.895,
            93.646,
            83.723
        ],
        "q0.25": [
            651.009,
            428.591,
            312.293,
            254.83,
            204.426
        ],
        "q0.5": [
            798.253,
            571.554,
            422.663,
            356.493,
            283.934
        ],
        "q0.75": [
            942.432,
            746.081,
            550.032,
            463.139,
            397.973
        ],
        "q0.975": [
            1220.331,
            1127.347,
            837.462,
            730.819,
            652.291
        ]
    },
    "CEPH-Rtrend_fluH": {
        "target_end_date": [
            "2024-02-03",
            "2024-02-10",
            "2024-02-17",
            "2024-02-24"
        ],
        "q0.025": [
            529.0,
            301.0,
            169.0,
            93.0
        ],
        "q0.25": [
            645.0,
            454.0,
            314.75,
            221.0
        ],
        "q0.5": [
            719.0,
            568.0,
            444.0,
            342.0
        ],
        "q0.75": [
            804.0,
            715.0,
            618.0,
            524.0
        ],
        "q0.975": [
            972.0,
            1037.0249999999996,
            1064.0249999999996,
            1023.0249999999996
        ]
    }
}